{"frames":{"cog_generic_1.png":{"frame":{"x":1,"y":1,"w":158,"h":162},"rotated":false,"trimmed":true,"spriteSourceSize":{"x":3,"y":1,"w":158,"h":162},"sourceSize":{"w":165,"h":165}},"cog_generic_2.png":{"frame":{"x":1,"y":165,"w":156,"h":160},"rotated":false,"trimmed":true,"spriteSourceSize":{"x":2,"y":0,"w":156,"h":160},"sourceSize":{"w":160,"h":160}},"cog_generic_3.png":{"frame":{"x":161,"y":1,"w":88,"h":96},"rotated":false,"trimmed":true,"spriteSourceSize":{"x":6,"y":2,"w":88,"h":96},"sourceSize":{"w":100,"h":100}},"cog_generic_4.png":{"frame":{"x":136,"y":339,"w":100,"h":100},"rotated":false,"trimmed":false,"spriteSourceSize":{"x":0,"y":0,"w":100,"h":100},"sourceSize":{"w":100,"h":100}},"cog_generic_5.png":{"frame":{"x":161,"y":99,"w":53,"h":54},"rotated":false,"trimmed":true,"spriteSourceSize":{"x":1,"y":0,"w":53,"h":54},"sourceSize":{"w":55,"h":55}},"cog_generic_6.png":{"frame":{"x":161,"y":155,"w":53,"h":54},"rotated":false,"trimmed":true,"spriteSourceSize":{"x":1,"y":0,"w":53,"h":54},"sourceSize":{"w":55,"h":55}},"colour-highlight.png":{"frame":{"x":159,"y":304,"w":38,"h":33},"rotated":false,"trimmed":true,"spriteSourceSize":{"x":13,"y":11,"w":38,"h":33},"sourceSize":{"w":95,"h":95}},"UI_curve_back.png":{"frame":{"x":1,"y":327,"w":133,"h":133},"rotated":false,"trimmed":false,"spriteSourceSize":{"x":0,"y":0,"w":133,"h":133},"sourceSize":{"w":133,"h":133}},"wheel_generic_button.png":{"frame":{"x":159,"y":211,"w":91,"h":91},"rotated":false,"trimmed":false,"spriteSourceSize":{"x":0,"y":0,"w":91,"h":91},"sourceSize":{"w":91,"h":91}}},"meta":{"app":"http://www.codeandweb.com/texturepacker","version":"1.0","image":"wheel0_mip.png","format":"RGBA8888","size":{"w":251,"h":461},"scale":"0.5","smartupdate":"$TexturePacker:SmartUpdate:ae0766a0a0032ae174b06ca9fb464872:df77d9a42f78a088374cb479085a9ea2:4af046c731f7ab35a0f5ef1b9855504f$"}}